flake8_os_walk/checker.py
flake8_os_walk-0.4.0.dist-info/LICENSE
flake8_os_walk-0.4.0.dist-info/METADATA
flake8_os_walk-0.4.0.dist-info/WHEEL
flake8_os_walk-0.4.0.dist-info/entry_points.txt
flake8_os_walk-0.4.0.dist-info/top_level.txt
flake8_os_walk-0.4.0.dist-info/RECORD
